wikiquotes/__init__.py
wikiquotes/wikiquotes_api.py
wikiquotes/languages/__init__.py
wikiquotes/languages/english.py
wikiquotes/languages/spanish.py
wikiquotes/managers/__init__.py
wikiquotes/managers/api_manager.py
wikiquotes/managers/custom_exceptions.py
wikiquotes/managers/file_manager.py
wikiquotes/managers/html_manager.py
wikiquotes/managers/json_parser.py
wikiquotes/managers/language_manager.py
wikiquotes/managers/logging_manager.py
wikiquotes-1.5.0.dist-info/licenses/LICENSE
wikiquotes-1.5.0.dist-info/METADATA
wikiquotes-1.5.0.dist-info/WHEEL
wikiquotes-1.5.0.dist-info/top_level.txt
wikiquotes-1.5.0.dist-info/RECORD
