Metadata-Version: 2.4
Name: wikiquotes
Version: 1.5.0
Summary: Wikiquotes python API
Author-email: Francisco Depascuali <francisco.depascuali@gmail.com>
License: MIT
Project-URL: Homepage, https://github.com/FranDepascuali/wikiquotes-python-api
Project-URL: Repository, https://github.com/FranDepascuali/wikiquotes-python-api
Project-URL: Bug Tracker, https://github.com/FranDepascuali/wikiquotes-python-api/issues
Classifier: Development Status :: 4 - Beta
Classifier: Intended Audience :: Developers
Classifier: Topic :: Software Development :: Libraries :: Python Modules
Classifier: License :: OSI Approved :: MIT License
Classifier: Programming Language :: Python :: 3
Classifier: Programming Language :: Python :: 3.10
Classifier: Programming Language :: Python :: 3.11
Classifier: Programming Language :: Python :: 3.12
Classifier: Programming Language :: Python :: 3.13
Requires-Python: >=3.10
License-File: LICENSE
Requires-Dist: beautifulsoup4>=4.9.0
Requires-Dist: requests>=2.25.0
Requires-Dist: lxml>=4.6.0
Requires-Dist: unidecode>=1.2.0
Provides-Extra: dev
Requires-Dist: pytest>=8.0.0; extra == "dev"
Requires-Dist: tox>=4.33.0; extra == "dev"
Dynamic: license-file
